scsmote_package/__init__.py
scsmote_package-0.0.2.dist-info/LICENSE
scsmote_package-0.0.2.dist-info/METADATA
scsmote_package-0.0.2.dist-info/WHEEL
scsmote_package-0.0.2.dist-info/top_level.txt
scsmote_package-0.0.2.dist-info/RECORD
