Metadata-Version: 2.1
Name: scsmote-package
Version: 0.0.2
Summary: A SMOTE variant called sematic-cosine SMOTE that generates textual synthetic data 
Home-page: https://github.com/hetulmehta/SC-SMOTE.git
Author: Hetul Mehta
Author-email: hetulmehta08@gmail.com
License: MIT
Requires-Python: >=3.8
License-File: LICENSE
